crader/__init__.py
crader/__main__.py
crader/config.py
crader/indexer.py
crader/manage_db.py
crader/models.py
crader/navigator.py
crader/py.typed
crader/reader.py
crader/retriever.py
crader/schema.py
crader/db/README
crader/db/alembic.ini
crader/db/env.py
crader/db/script.py.mako
crader/db/versions/c7afc7db3cb4_initial_schema.py
crader/embedding/embedder.py
crader/graph/__init__.py
crader/graph/base.py
crader/graph/builder.py
crader/graph/indexers/__init__.py
crader/graph/indexers/scip.py
crader/parsing/__init__.py
crader/parsing/parser.py
crader/parsing/parsing_filters.py
crader/parsing/queries/javascript.scm
crader/parsing/queries/python.scm
crader/parsing/queries/typescript.scm
crader/providers/__init__.py
crader/providers/embedding.py
crader/providers/metadata.py
crader/retrieval/__init__.py
crader/retrieval/graph_walker.py
crader/retrieval/rankers.py
crader/retrieval/searcher.py
crader/storage/__init__.py
crader/storage/base.py
crader/storage/connector.py
crader/storage/postgres.py
crader/storage/sqlite.py
crader/utils/__init__.py
crader/utils/git.py
crader/utils/hashing.py
crader/volume_manager/__init__.py
crader/volume_manager/git_volume_manager.py
crader-0.1.0.dist-info/licenses/LICENSE
crader-0.1.0.dist-info/METADATA
crader-0.1.0.dist-info/WHEEL
crader-0.1.0.dist-info/entry_points.txt
crader-0.1.0.dist-info/top_level.txt
crader-0.1.0.dist-info/RECORD
