Metadata-Version: 2.4
Name: crader
Version: 0.1.0
Summary: Crader is a production-ready library that transforms source code into a queryable Code Property Graph (CPG) with semantic embeddings. Built for AI-powered code analysis, intelligent retrieval, and agentic workflows.
Author: Sheep Technologies
License: MIT License
Project-URL: Homepage, https://sheeptechnologies.github.io/crader/
Project-URL: Repository, https://github.com/sheeptechnologies/crader
Project-URL: Issues, https://github.com/sheeptechnologies/crader/issues
Keywords: code-analysis,graph,tree-sitter,scip,indexing
Classifier: Development Status :: 3 - Alpha
Classifier: Intended Audience :: Developers
Classifier: License :: OSI Approved :: MIT License
Classifier: Programming Language :: Python :: 3
Classifier: Programming Language :: Python :: 3.10
Classifier: Operating System :: OS Independent
Requires-Python: >=3.10
License-File: LICENSE
Requires-Dist: networkx>=3.0
Requires-Dist: tree-sitter==0.21.3
Requires-Dist: tree-sitter-languages==1.8.0
Requires-Dist: alembic>=1.7.0
Requires-Dist: click>=8.0
Requires-Dist: GitPython>=3.1
Requires-Dist: openai>=1.0.0
Requires-Dist: opentelemetry-api>=1.0.0
Requires-Dist: pgvector>=0.2.0
Requires-Dist: psycopg>=3.1.0
Requires-Dist: psycopg-pool>=3.1.0
Requires-Dist: pydantic>=2.0.0
Requires-Dist: tenacity>=8.0.0
Requires-Dist: python-dotenv>=1.0.0
Provides-Extra: dev
Requires-Dist: pytest>=7.0; extra == "dev"
Requires-Dist: pytest-cov>=4.0; extra == "dev"
Requires-Dist: ruff>=0.1.0; extra == "dev"
Requires-Dist: mypy>=1.0.0; extra == "dev"
Requires-Dist: build>=1.0.0; extra == "dev"
Requires-Dist: twine>=4.0.0; extra == "dev"
Requires-Dist: types-requests; extra == "dev"
Requires-Dist: types-PyYAML; extra == "dev"
Requires-Dist: alembic>=1.7.0; extra == "dev"
Requires-Dist: psycopg2-binary>=2.9.0; extra == "dev"
Dynamic: license-file
